ailia_llm/LICENSE_AILIA_EN.pdf
ailia_llm/LICENSE_AILIA_JA.pdf
ailia_llm/__init__.py
ailia_llm/linux/x64/libailia_llm.so
ailia_llm/mac/libailia_llm.dylib
ailia_llm/oss/LICENSE_LLAMA_CPP.txt
ailia_llm/windows/x64/ailia_llm.dll
ailia_llm/windows/x64/ailia_llm_fallback.dll
ailia_llm/windows/x64/ggml-base.dll
ailia_llm/windows/x64/ggml-cpu.dll
ailia_llm/windows/x64/ggml-rpc.dll
ailia_llm/windows/x64/ggml-vulkan.dll
ailia_llm/windows/x64/ggml.dll
ailia_llm/windows/x64/llama.dll
ailia_llm-1.3.3.1.data/scripts/__init__.py
ailia_llm-1.3.3.1.dist-info/METADATA
ailia_llm-1.3.3.1.dist-info/WHEEL
ailia_llm-1.3.3.1.dist-info/top_level.txt
ailia_llm-1.3.3.1.dist-info/RECORD
