Metadata-Version: 2.4
Name: ailia_llm
Version: 1.3.3.1
Summary: ailia LLM
Home-page: https://ailia.jp/
Author: ax Inc.
Author-email: contact@axinc.jp
License: https://ailia.ai/en/license/
Requires-Python: >3.6
Requires-Dist: ailia
Dynamic: author
Dynamic: author-email
Dynamic: description
Dynamic: description-content-type
Dynamic: home-page
Dynamic: license
Dynamic: requires-dist
Dynamic: requires-python
Dynamic: summary
